handsom/__init__.py
handsom/boy/__init__.py
handsom/boy/information.py
handsom/boy/messag.py
zzw.py-0.1.dist-info/METADATA
zzw.py-0.1.dist-info/WHEEL
zzw.py-0.1.dist-info/top_level.txt
zzw.py-0.1.dist-info/RECORD
