Metadata-Version: 2.1
Name: zzw.py
Version: 0.1
Summary: 曾卓文，林镇坤
Author: zzw
License: UNKNOWN
Platform: UNKNOWN
